{"data": [{"AC": {"fecha": "2017-10-01 00:00:00", "provincia": "A CORU\u00d1A", "fillKey": "NORTE", "percentage_acc": 81.23861566484516, "increment": 0.295823575331772}}, {"AL": {"fecha": "2017-10-01 00:00:00", "provincia": "ALBACETE", "fillKey": "CENTRO", "percentage_acc": 98.23008849557523, "increment": 0.11725663716814158}}, {"AY": {"fecha": "2017-10-01 00:00:00", "provincia": "ALICANTE/ALACANT", "fillKey": "ESTE", "percentage_acc": 86.63252692918948, "increment": 0.2924686561892989}}, {"AX": {"fecha": "2017-10-01 00:00:00", "provincia": "ALMERIA", "fillKey": "SUR", "percentage_acc": 83.69515011547344, "increment": 0.38372979214780606}}, {"AB": {"fecha": "2017-10-01 00:00:00", "provincia": "ARABA/ALAVA", "fillKey": "NORTE", "percentage_acc": 96.12068965517241, "increment": 0.09423491379310345}}, {"AS": {"fecha": "2017-10-01 00:00:00", "provincia": "ASTURIAS", "fillKey": "NORTE", "percentage_acc": 95.08357915437561, "increment": 0.11986234021632251}}, {"AV": {"fecha": "2017-10-01 00:00:00", "provincia": "AVILA", "fillKey": "CENTRO", "percentage_acc": 87.6, "increment": 0.053}}, {"BZ": {"fecha": "2017-10-01 00:00:00", "provincia": "BADAJOZ", "fillKey": "SUR", "percentage_acc": 93.22678843226788, "increment": 0.2541095890410959}}, {"BR": {"fecha": "2017-10-01 00:00:00", "provincia": "BARCELONA", "fillKey": "CATALUNYA", "percentage_acc": 89.52994204764971, "increment": 0.2603927881519639}}, {"BI": {"fecha": "2017-10-01 00:00:00", "provincia": "BIZKAIA", "fillKey": "NORTE", "percentage_acc": 91.4804469273743, "increment": 0.285911312849162}}, {"BU": {"fecha": "2017-10-01 00:00:00", "provincia": "BURGOS", "fillKey": "CENTRO", "percentage_acc": 92.87671232876713, "increment": 0.3121917808219178}}, {"CA": {"fecha": "2017-10-01 00:00:00", "provincia": "CACERES", "fillKey": "SUR", "percentage_acc": 95.52572706935123, "increment": 0.04742729306487695}}, {"CZ": {"fecha": "2017-10-01 00:00:00", "provincia": "CADIZ", "fillKey": "SUR", "percentage_acc": 91.1667765326302, "increment": 0.21719402329158422}}, {"CR": {"fecha": "2017-10-01 00:00:00", "provincia": "CANTABRIA", "fillKey": "NORTE", "percentage_acc": 96.93945442448437, "increment": 0.22920825016633398}}, {"CS": {"fecha": "2017-10-01 00:00:00", "provincia": "CASTELLON/CASTELL\u00d3", "fillKey": "ESTE", "percentage_acc": 79.5048143053645, "increment": 0.3601375515818432}}, {"CU": {"fecha": "2017-10-01 00:00:00", "provincia": "CEUTA", "fillKey": "SUR", "percentage_acc": 77.35849056603773, "increment": 1.0}}, {"CE": {"fecha": "2017-10-01 00:00:00", "provincia": "CIUDAD REAL", "fillKey": "CENTRO", "percentage_acc": 89.69072164948453, "increment": 0.2276632302405498}}, {"CO": {"fecha": "2017-10-01 00:00:00", "provincia": "CORDOBA", "fillKey": "SUR", "percentage_acc": 78.51063829787235, "increment": 0.3082269503546099}}, {"CC": {"fecha": "2017-10-01 00:00:00", "provincia": "CUENCA", "fillKey": "CENTRO", "percentage_acc": 86.18266978922716, "increment": 0.16756440281030444}}, {"GK": {"fecha": "2017-10-01 00:00:00", "provincia": "GIPUZKOA", "fillKey": "NORTE", "percentage_acc": 88.3899935856318, "increment": 0.05949326491340602}}, {"GI": {"fecha": "2017-10-01 00:00:00", "provincia": "GIRONA", "fillKey": "CATALUNYA", "percentage_acc": 95.4113924050633, "increment": 0.4123154008438818}}, {"GR": {"fecha": "2017-10-01 00:00:00", "provincia": "GRANADA", "fillKey": "SUR", "percentage_acc": 84.30505664548217, "increment": 0.17793589389334072}}, {"GU": {"fecha": "2017-10-01 00:00:00", "provincia": "GUADALAJARA", "fillKey": "CENTRO", "percentage_acc": 94.26681367144432, "increment": 0.36521499448732087}}, {"HU": {"fecha": "2017-10-01 00:00:00", "provincia": "HUELVA", "fillKey": "SUR", "percentage_acc": 91.23287671232877, "increment": 0.4327123287671233}}, {"HS": {"fecha": "2017-10-01 00:00:00", "provincia": "HUESCA", "fillKey": "NORTE", "percentage_acc": 94.28904428904428, "increment": 0.4694638694638694}}, {"IB": {"fecha": "2017-10-01 00:00:00", "provincia": "ILLES BALEARS", "fillKey": "ESTE", "percentage_acc": 84.49873631002527, "increment": 0.1406486941870261}}, {"JA": {"fecha": "2017-10-01 00:00:00", "provincia": "JAEN", "fillKey": "SUR", "percentage_acc": 74.94887525562372, "increment": 0.2926380368098159}}, {"LR": {"fecha": "2017-10-01 00:00:00", "provincia": "LA RIOJA", "fillKey": "NORTE", "percentage_acc": 76.86541737649063, "increment": 0.5327086882453151}}, {"TP": {"fecha": "2017-10-01 00:00:00", "provincia": "LAS PALMAS", "fillKey": "CANARIAS", "percentage_acc": 90.01584786053883, "increment": 0.3603328050713153}}, {"LE": {"fecha": "2017-10-01 00:00:00", "provincia": "LEON", "fillKey": "CENTRO", "percentage_acc": 88.0503144654088, "increment": 0.175}}, {"LL": {"fecha": "2017-10-01 00:00:00", "provincia": "LLEIDA", "fillKey": "CATALUNYA", "percentage_acc": 87.89850357839947, "increment": 0.27413793103448275}}, {"LU": {"fecha": "2017-10-01 00:00:00", "provincia": "LUGO", "fillKey": "NORTE", "percentage_acc": 87.6068376068376, "increment": 0.1472222222222222}}, {"MD": {"fecha": "2017-10-01 00:00:00", "provincia": "MADRID", "fillKey": "CENTRO", "percentage_acc": 87.71043771043772, "increment": 0.2985625485625486}}, {"MA": {"fecha": "2017-10-01 00:00:00", "provincia": "MALAGA", "fillKey": "SUR", "percentage_acc": 88.85472713297463, "increment": 0.23220599538816292}}, {"MU": {"fecha": "2017-10-01 00:00:00", "provincia": "MURCIA", "fillKey": "ESTE", "percentage_acc": 83.36427775714816, "increment": 0.35326773115484583}}, {"NV": {"fecha": "2017-10-01 00:00:00", "provincia": "NAVARRA", "fillKey": "NORTE", "percentage_acc": 96.3076923076923, "increment": 0.057076923076923074}}, {"OU": {"fecha": "2017-10-01 00:00:00", "provincia": "OURENSE", "fillKey": "NORTE", "percentage_acc": 95.95375722543353, "increment": 0.0}}, {"PA": {"fecha": "2017-10-01 00:00:00", "provincia": "PALENCIA", "fillKey": "CENTRO", "percentage_acc": 96.21342512908778, "increment": 0.009122203098106713}}, {"PO": {"fecha": "2017-10-01 00:00:00", "provincia": "PONTEVEDRA", "fillKey": "NORTE", "percentage_acc": 92.89514866979654, "increment": 0.12690140845070422}}, {"SA": {"fecha": "2017-10-01 00:00:00", "provincia": "SALAMANCA", "fillKey": "CENTRO", "percentage_acc": 88.34134615384616, "increment": 0.2261418269230769}}, {"TP": {"fecha": "2017-10-01 00:00:00", "provincia": "SANTA CRUZ DE TENERIFE", "fillKey": "CANARIAS", "percentage_acc": 72.31200527704486, "increment": 0.1944673482849604}}, {"SE": {"fecha": "2017-10-01 00:00:00", "provincia": "SEGOVIA", "fillKey": "CENTRO", "percentage_acc": 95.14963880288958, "increment": 0.10939112487100103}}, {"SV": {"fecha": "2017-10-01 00:00:00", "provincia": "SEVILLA", "fillKey": "SUR", "percentage_acc": 76.30297565374211, "increment": 0.35126239855725877}}, {"SO": {"fecha": "2017-10-01 00:00:00", "provincia": "SORIA", "fillKey": "CENTRO", "percentage_acc": 83.60128617363343, "increment": 0.30249196141479096}}, {"TA": {"fecha": "2017-10-01 00:00:00", "provincia": "TARRAGONA", "fillKey": "CATALUNYA", "percentage_acc": 85.93342981186687, "increment": 0.4724746743849494}}, {"TO": {"fecha": "2017-10-01 00:00:00", "provincia": "TOLEDO", "fillKey": "CENTRO", "percentage_acc": 91.72477917247792, "increment": 0.2864365411436541}}, {"VA": {"fecha": "2017-10-01 00:00:00", "provincia": "VALENCIA", "fillKey": "ESTE", "percentage_acc": 86.13096387869422, "increment": 0.29381881398493337}}, {"VL": {"fecha": "2017-10-01 00:00:00", "provincia": "VALLADOLID", "fillKey": "CENTRO", "percentage_acc": 88.28169014084507, "increment": 0.3224788732394366}}, {"ZA": {"fecha": "2017-10-01 00:00:00", "provincia": "ZAMORA", "fillKey": "CENTRO", "percentage_acc": 83.33333333333334, "increment": 0.13249999999999998}}, {"ZR": {"fecha": "2017-10-01 00:00:00", "provincia": "ZARAGOZA", "fillKey": "NORTE", "percentage_acc": 90.30748663101605, "increment": 0.2940508021390374}}, {"TE": {"fecha": "2017-10-01", "provincia": "TERUEL", "fillKey": "NORTE", "percentage_acc": 91.75257731958762, "increment": 0}}, {"ME": {"fecha": "2017-10-01", "provincia": "MELILLA", "fillKey": "SUR", "percentage_acc": 83.33333333333331, "increment": 0}}]}