{"data": [{"AB": {"fecha": "2011-07-01 00:00:00", "provincia": "ARABA/ALAVA", "fillKey": "NORTE", "percentage_acc": 98.68351764086361, "increment": 0.0}}, {"AS": {"fecha": "2011-07-01 00:00:00", "provincia": "ASTURIAS", "fillKey": "NORTE", "percentage_acc": 98.3790523690773, "increment": 0.3553615960099751}}, {"BR": {"fecha": "2011-07-01 00:00:00", "provincia": "BARCELONA", "fillKey": "CATALUNYA", "percentage_acc": 54.99092271404059, "increment": 0.14062323151380154}}, {"BU": {"fecha": "2011-07-01 00:00:00", "provincia": "BURGOS", "fillKey": "CENTRO", "percentage_acc": 99.52718676122932, "increment": 0.03309692671394799}}, {"CS": {"fecha": "2011-07-01 00:00:00", "provincia": "CASTELLON/CASTELL\u00d3", "fillKey": "ESTE", "percentage_acc": 100.0, "increment": 0.012437810945273632}}, {"CU": {"fecha": "2011-07-01 00:00:00", "provincia": "CEUTA", "fillKey": "SUR", "percentage_acc": 100.0, "increment": 1.0}}, {"GK": {"fecha": "2011-07-01 00:00:00", "provincia": "GIPUZKOA", "fillKey": "NORTE", "percentage_acc": 97.60717846460619, "increment": 0.006979062811565304}}, {"GR": {"fecha": "2011-07-01 00:00:00", "provincia": "GRANADA", "fillKey": "SUR", "percentage_acc": 85.79387186629526, "increment": 0.14763231197771587}}, {"MD": {"fecha": "2011-07-01 00:00:00", "provincia": "MADRID", "fillKey": "CENTRO", "percentage_acc": 57.48071924666581, "increment": 0.10069879415399036}}, {"SE": {"fecha": "2011-07-01 00:00:00", "provincia": "SEGOVIA", "fillKey": "CENTRO", "percentage_acc": 97.63779527559055, "increment": 0.0}}, {"SV": {"fecha": "2011-07-01 00:00:00", "provincia": "SEVILLA", "fillKey": "SUR", "percentage_acc": 47.289972899728994, "increment": 0.06707317073170732}}, {"VA": {"fecha": "2011-07-01 00:00:00", "provincia": "VALENCIA", "fillKey": "ESTE", "percentage_acc": 72.24880382775119, "increment": 0.20574162679425836}}, {"VL": {"fecha": "2011-07-01 00:00:00", "provincia": "VALLADOLID", "fillKey": "CENTRO", "percentage_acc": 78.38903170522708, "increment": 0.08431876606683804}}, {"ZR": {"fecha": "2011-07-01 00:00:00", "provincia": "ZARAGOZA", "fillKey": "NORTE", "percentage_acc": 94.86644407345577, "increment": 0.03763216471897607}}]}